pyfetcher_vaaai/__init__.py
pyfetcher_vaaai/main.py
pyfetcher_vaaai-1.7.2.dist-info/METADATA
pyfetcher_vaaai-1.7.2.dist-info/WHEEL
pyfetcher_vaaai-1.7.2.dist-info/licenses/LICENSE
pyfetcher_vaaai-1.7.2.dist-info/RECORD
