Metadata-Version: 2.3
Name: pyfetcher_vaaai
Version: 1.7.2
Summary: PyFetch for Windows
Author-email: Vaaai <vaaai@42.fr>
License-File: LICENSE
Classifier: License :: OSI Approved :: MIT License
Classifier: Operating System :: OS Independent
Classifier: Programming Language :: Python :: 3
Requires-Python: >=3.8
